MANIFEST.in
setup.py
finalseg/__init__.py
finalseg/__init__.pyc
finalseg/near_char_tab.txt
finalseg/prob_emit.py
finalseg/prob_start.py
finalseg/prob_trans.py
finalseg.egg-info/PKG-INFO
finalseg.egg-info/SOURCES.txt
finalseg.egg-info/dependency_links.txt
finalseg.egg-info/not-zip-safe
finalseg.egg-info/top_level.txt