Metadata-Version: 1.0
Name: finalseg
Version: 0.1
Summary: A Chinese Words Segmentation Library
Home-page: UNKNOWN
Author: Sun, Junyi
Author-email: zsp042@gmail.com
License: UNKNOWN
Platform: UNKNOWN
